app_context/__init__.py
app_context-0.9.0.dist-info/LICENSE
app_context-0.9.0.dist-info/METADATA
app_context-0.9.0.dist-info/WHEEL
app_context-0.9.0.dist-info/top_level.txt
app_context-0.9.0.dist-info/RECORD
